data_prep_helper/__init__.py
data_prep_helper/data.py
data_prep_helper/data_prep_helper.py
data_prep_helper-0.0.3.dist-info/LICENSE
data_prep_helper-0.0.3.dist-info/METADATA
data_prep_helper-0.0.3.dist-info/WHEEL
data_prep_helper-0.0.3.dist-info/top_level.txt
data_prep_helper-0.0.3.dist-info/RECORD
