Metadata-Version: 2.1
Name: data-prep-helper
Version: 0.0.3
Summary: A helper library for data prepration from multiple sources
Home-page: https://github.com/ngupta23/data_prep_helper
Author: Nikhil Gupta
Author-email: mywork.ng@gmail.com
License: UNKNOWN
Platform: UNKNOWN
Classifier: Programming Language :: Python :: 3
Classifier: License :: OSI Approved :: MIT License
Classifier: Operating System :: OS Independent
